{"chunk_definitions":[{"row":9,"row_count":1,"visible":true,"expansion_state":0,"options":{"engine":"r","label":"unnamed-chunk-6","dev":"png"},"document_id":"5F668423","chunk_id":"cc9rckz4m3745","chunk_label":"unnamed-chunk-1"},{"row":18,"row_count":1,"visible":true,"expansion_state":0,"options":{"engine":"python","label":"unnamed-chunk-7","dev":"png"},"document_id":"5F668423","chunk_id":"cvkuttccklzpz","chunk_label":"unnamed-chunk-2"},{"row":29,"row_count":1,"visible":true,"expansion_state":0,"options":{"engine":"python","label":"unnamed-chunk-29","dev":"png"},"document_id":"5F668423","chunk_id":"cdcu9f1ykk2ee","chunk_label":"unnamed-chunk-3"},{"row":38,"row_count":1,"visible":true,"expansion_state":0,"options":{"engine":"python","label":"unnamed-chunk-30","dev":"png"},"document_id":"5F668423","chunk_id":"c50nyzq1pyktt","chunk_label":"unnamed-chunk-4"},{"row":47,"row_count":1,"visible":true,"expansion_state":0,"options":{"engine":"python","label":"unnamed-chunk-31","dev":"png"},"document_id":"5F668423","chunk_id":"cewtw0x64mqna","chunk_label":"unnamed-chunk-5"},{"row":61,"row_count":1,"visible":true,"expansion_state":0,"options":{"engine":"python","label":"unnamed-chunk-6","dev":"png"},"document_id":"5F668423","chunk_id":"c4zid85x71s8o","chunk_label":"unnamed-chunk-6"},{"row":72,"row_count":1,"visible":true,"expansion_state":0,"options":{"engine":"python","label":"unnamed-chunk-7","dev":"png"},"document_id":"5F668423","chunk_id":"chr3skxs8iapz","chunk_label":"unnamed-chunk-7"}],"doc_write_time":1713767397}